scself/__init__.py
scself/_denoise/__init__.py
scself/_denoise/n2s_denoise.py
scself/_mcv/__init__.py
scself/_mcv/common.py
scself/_mcv/mcv_per_cell.py
scself/_mcv/molecular_crossvalidation.py
scself/_modules/__init__.py
scself/_modules/find_modules.py
scself/_modules/find_weighted_modules.py
scself/_modules/score_modules.py
scself/_noise2self/__init__.py
scself/_noise2self/common.py
scself/_noise2self/graph.py
scself/_noise2self/multimodal_n2s.py
scself/_noise2self/n2s.py
scself/scaling/__init__.py
scself/scaling/truncscaler.py
scself/sparse/__init__.py
scself/sparse/graph.py
scself/sparse/math.py
scself/tests/__init__.py
scself/tests/_stubs.py
scself/tests/test_correlation.py
scself/tests/test_denoise.py
scself/tests/test_math.py
scself/tests/test_mcv.py
scself/tests/test_modules.py
scself/tests/test_noise2self.py
scself/tests/test_pca.py
scself/tests/test_score_modules.py
scself/tests/test_sparse_math.py
scself/tests/test_standardization.py
scself/tests/test_weighted_modules.py
scself/utils/__init__.py
scself/utils/_pca.py
scself/utils/cast_dtype_inplace.py
scself/utils/correlation.py
scself/utils/dot_product.py
scself/utils/hierarchical_clustering.py
scself/utils/logging.py
scself/utils/pairwise_loss.py
scself/utils/shrink.py
scself/utils/standardization.py
scself/utils/sum.py
scself-0.5.0.dist-info/licenses/LICENSE
scself-0.5.0.dist-info/METADATA
scself-0.5.0.dist-info/WHEEL
scself-0.5.0.dist-info/top_level.txt
scself-0.5.0.dist-info/RECORD
